bumpytrack.py
bumpytrack-1.1.7.dist-info/LICENSE
bumpytrack-1.1.7.dist-info/METADATA
bumpytrack-1.1.7.dist-info/WHEEL
bumpytrack-1.1.7.dist-info/entry_points.txt
bumpytrack-1.1.7.dist-info/top_level.txt
bumpytrack-1.1.7.dist-info/RECORD
