Metadata-Version: 2.1
Name: bumpytrack
Version: 1.1.7
Summary: Simple semantic-version bumper in python that works.
Home-page: https://github.com/nandilugio/bumpytrack
Author: Fernando Stecconi
Author-email: nandilugio@gmail.com
License: MIT
Classifier: Programming Language :: Python :: 3
Classifier: License :: OSI Approved :: MIT License
Classifier: Operating System :: OS Independent
License-File: LICENSE
Requires-Dist: toml >=0.9.4
